glacius/__init__.py
glacius/aggregation.py
glacius/client.py
glacius/data_sources/__init__.py
glacius/data_sources/file.py
glacius/data_sources/redshift.py
glacius/data_sources/registry.py
glacius/data_sources/snowflake.py
glacius/data_sources/source.py
glacius/dsl.py
glacius/dtypes.py
glacius/entity.py
glacius/feature.py
glacius/feature_bundle.py
glacius/hash_utils.py
glacius/job.py
glacius/tests/test_dsl.py
glacius-0.0.8.dist-info/LICENSE
glacius-0.0.8.dist-info/METADATA
glacius-0.0.8.dist-info/WHEEL
glacius-0.0.8.dist-info/RECORD
