Metadata-Version: 2.1
Name: glacius
Version: 0.0.8
Summary: The Enterprise Feature Store For Machine Learning
Author: Andrew T
Author-email: atreeleaf@gmail.com
Requires-Python: >=3.9,<4.0
Classifier: Programming Language :: Python :: 3
Classifier: Programming Language :: Python :: 3.9
Classifier: Programming Language :: Python :: 3.10
Classifier: Programming Language :: Python :: 3.11
Requires-Dist: requests (>=2.31.0,<3.0.0)
